<?xml version="1.0" encoding="utf-8"?>
<Trips>
  <Trip>
    <ID>831</ID>
    <Origin>تهران، میدان بسیج، افسریه، سی و پنج متری قصرفیروزه</Origin>
    <Destination>تهران، چهارراه ولیعصر</Destination>
    <RegiterDateTime>5:28:42 - 1393/8/3</RegiterDateTime>
    <Cost>200000</Cost>
    <Description></Description>
  </Trip>
  <Trip>
    <ID>833</ID>
    <Origin>تهران، میدان قدس</Origin>
    <Destination>تهران، میدان ولیعصر</Destination>
    <RegiterDateTime>7:40:24 - 1393/8/3</RegiterDateTime>
    <Cost>200000</Cost>
    <Description></Description>
  </Trip>
  <Trip>
    <ID>834</ID>
    <Origin>تهران، میدان اتریش</Origin>
    <Destination>تهران ، میدان آزادی</Destination>
    <RegiterDateTime>8:0:45 - 1393/8/3</RegiterDateTime>
    <Cost>300000</Cost>
    <Description></Description>
  </Trip>
  <Trip>
    <ID>067af495-dd06-444b-8191-603e37512143</ID>
    <Origin>تست</Origin>
    <Destination>تست</Destination>
    <RegisterDateTime>10:4:19 - 1393/8/4</RegisterDateTime>
    <Cost>8000000</Cost>
    <Description>تستی</Description>
  </Trip>
</Trips>